src/__init__.py
src/ComandLineInterface/Interface.py
src/ComandLineInterface/__init__.py
src/Controller/__init__.py
src/Model/Framework.py
src/Model/__init__.py
src/Model/DataBase/__init__.py
src/Model/DataBase/MyDB/Database_module.py
src/Model/DataBase/MyDB/__init__.py
src/Model/DataBase/MyDB/exceptions/DataBaseExceptions.py
src/Model/DataBase/MyDB/exceptions/__init__.py
src/Model/Entities/Administration_Unit.py
src/Model/Entities/Entity.py
src/Model/Entities/__init__.py
src/Model/Entities/Environment/__init__.py
src/Model/Entities/Environment/Installation/Execution_Unit.py
src/Model/Entities/Environment/Installation/Repositories.py
src/Model/Entities/Environment/Installation/__init__.py
src/Model/Entities/Environment/Installation/Grammar/Grammar.py
src/Model/Entities/Environment/Installation/Grammar/__init__.py
src/Model/Entities/Environment/Installation/Grammar/demiurge-grammar-generator-full.py
src/Model/Entities/Environment/Installation/exceptions/ClusterExceptions.py
src/Model/Entities/Environment/Installation/exceptions/__init__.py
src/Model/Entities/Environment/Simulation/__init__.py
swarmDesign-0.0.1.dist-info/METADATA
swarmDesign-0.0.1.dist-info/WHEEL
swarmDesign-0.0.1.dist-info/entry_points.txt
swarmDesign-0.0.1.dist-info/top_level.txt
swarmDesign-0.0.1.dist-info/RECORD
